msdss_base_api/__init__.py
msdss_base_api/core.py
msdss_base_api-0.0.0.dist-info/LICENSE
msdss_base_api-0.0.0.dist-info/METADATA
msdss_base_api-0.0.0.dist-info/WHEEL
msdss_base_api-0.0.0.dist-info/top_level.txt
msdss_base_api-0.0.0.dist-info/RECORD
